{
    "872275": {
        "gpjs": 8,
        "zqdm": "松华新材",
        "zqjc": "872275",
        "sshy": "橡胶和塑料制品业",
        "zbqs": "东莞证券",
        "mgsy": 0.09,
        "mgjzc": 1.15,
        "jlrtbzz": 0,
        "jzcsyl": 0.08,
        "zgb": 14880000,
        "ltgb": 0
    },
    "872341": {
        "gpjs": 8,
        "zqdm": "同泽股份",
        "zqjc": "872341",
        "sshy": "专业技术服务业",
        "zbqs": "申万宏源证券",
        "mgsy": 0.38,
        "mgjzc": 3.07,
        "jlrtbzz": 0,
        "jzcsyl": 0.13,
        "zgb": 10000000,
        "ltgb": 0
    },
    "872329": {
        "gpjs": 8,
        "zqdm": "冠翔生物",
        "zqjc": "872329",
        "sshy": "零售业",
        "zbqs": "华龙证券",
        "mgsy": 0.06,
        "mgjzc": 1.48,
        "jlrtbzz": 0,
        "jzcsyl": 0.04,
        "zgb": 10000000,
        "ltgb": 0
    },
    "872315": {
        "gpjs": 8,
        "zqdm": "威骏股份",
        "zqjc": "872315",
        "sshy": "批发业",
        "zbqs": "西部证券",
        "mgsy": 0.04,
        "mgjzc": 1.48,
        "jlrtbzz": 0,
        "jzcsyl": 0.03,
        "zgb": 43000000,
        "ltgb": 14725000
    },
    "872296": {
        "gpjs": 8,
        "zqdm": "格林春天",
        "zqjc": "872296",
        "sshy": "化学原料和化学制品制造业",
        "zbqs": "万联证券",
        "mgsy": 0,
        "mgjzc": 1.09,
        "jlrtbzz": 0,
        "jzcsyl": 0,
        "zgb": 30000000,
        "ltgb": 0
    },
    "872295": {
        "gpjs": 8,
        "zqdm": "宗兴合泰",
        "zqjc": "872295",
        "sshy": "专业技术服务业",
        "zbqs": "宗兴合泰",
        "mgsy": -0.01,
        "mgjzc": 1.26,
        "jlrtbzz": 0,
        "jzcsyl": -0.01,
        "zgb": 6000000,
        "ltgb": 0
    },
    "872303": {
        "gpjs": 8,
        "zqdm": "自 由 能",
        "zqjc": "872303",
        "sshy": "化学原料和化学制品制造业",
        "zbqs": "东莞证券",
        "mgsy": 1,
        "mgjzc": 2.35,
        "jlrtbzz": 0,
        "jzcsyl": 0.54,
        "zgb": 24000000,
        "ltgb": 0
    },
    "872339": {
        "gpjs": 8,
        "zqdm": "光锐通信",
        "zqjc": "872339",
        "sshy": "计算机、通信和其他电子设备制造业",
        "zbqs": "国元证券",
        "mgsy": -0.06,
        "mgjzc": 1.06,
        "jlrtbzz": 0,
        "jzcsyl": -0.1,
        "zgb": 8500000,
        "ltgb": 2100000
    }
}
